{"config_name": "clock_0days",
 "long": {"backwards_tp": true,
          "delay_between_fills_minutes_close": 1143.5104758977973,
          "delay_between_fills_minutes_entry": 1090.113364954926,
          "delay_weight_close": 29.976295470832362,
          "delay_weight_entry": 11.176737453498339,
          "ema_dist_close": 0.0011913388741614705,
          "ema_dist_entry": -0.010974320446217562,
          "ema_span_0": 546.7128913884131,
          "ema_span_1": 1430.4865462558662,
          "enabled": true,
          "markup_range": 0.010664419859808712,
          "min_markup": 0.0058787981942411555,
          "n_close_orders": 13,
          "qty_pct_close": 0.01,
          "qty_pct_entry": 0.010539175732125268,
          "wallet_exposure_limit": 1,
          "we_multiplier_close": 0,
          "we_multiplier_entry": 24.42717123756755},
 "short": {"backwards_tp": true,
           "delay_between_fills_minutes_close": 1204.4546701711274,
           "delay_between_fills_minutes_entry": 1128.1408534064008,
           "delay_weight_close": 16.678306635091506,
           "delay_weight_entry": 8.85516848053756,
           "ema_dist_close": -0.003818699394040435,
           "ema_dist_entry": -0.007529238148379888,
           "ema_span_0": 1316.8704868026111,
           "ema_span_1": 1048.413572357066,
           "enabled": true,
           "markup_range": 0.02711580065855055,
           "min_markup": 0.0037526765235939264,
           "n_close_orders": 5,
           "qty_pct_close": 0.011394630718400411,
           "qty_pct_entry": 0.012983194494298482,
           "wallet_exposure_limit": 1,
           "we_multiplier_close": 0,
           "we_multiplier_entry": 45.34142025772678}}