{"config_name": "clock_0days",
 "long": {"backwards_tp": true,
          "delay_between_fills_minutes_close": 1186.2798097626264,
          "delay_between_fills_minutes_entry": 1099.0053381747416,
          "delay_weight_close": 13.226221412387021,
          "delay_weight_entry": 26.40594905488671,
          "ema_dist_close": -0.0038524493339151273,
          "ema_dist_entry": 0.002172870650925028,
          "ema_span_0": 132.028447833531,
          "ema_span_1": 316.73249819472977,
          "enabled": true,
          "markup_range": 0.005030180498700875,
          "min_markup": 0.004176474987184056,
          "n_close_orders": 3,
          "qty_pct_close": 0.01550170830279334,
          "qty_pct_entry": 0.016004554071441482,
          "wallet_exposure_limit": 1,
          "we_multiplier_close": 0,
          "we_multiplier_entry": 28.7847910142078},
 "short": {"backwards_tp": true,
           "delay_between_fills_minutes_close": 926.8401824718923,
           "delay_between_fills_minutes_entry": 565.9102557972923,
           "delay_weight_close": 7.115927486106189,
           "delay_weight_entry": 5.886435124435912,
           "ema_dist_close": 0.002598127617680403,
           "ema_dist_entry": -0.004747067344375997,
           "ema_span_0": 1199.1173840814245,
           "ema_span_1": 1056.4427610127157,
           "enabled": true,
           "markup_range": 0.004073388569302741,
           "min_markup": 0.0023687164650121285,
           "n_close_orders": 14,
           "qty_pct_close": 0.021899763344203613,
           "qty_pct_entry": 0.016574597833629023,
           "wallet_exposure_limit": 1,
           "we_multiplier_close": 0,
           "we_multiplier_entry": 44.6205871831539}}