{"config_name": "recursive_grid_0days",
 "logging_level": 0,
 "long": {"auto_unstuck_delay_minutes": 0,
          "auto_unstuck_ema_dist": 0,
          "auto_unstuck_qty_pct": 0,
          "auto_unstuck_wallet_exposure_threshold": 0.0,
          "backwards_tp": true,
          "ddown_factor": 2.573826907856526,
          "ema_span_0": 625.2193451640411,
          "ema_span_1": 647.7695806479344,
          "enabled": true,
          "initial_eprice_ema_dist": -0.0011800966163447765,
          "initial_qty_pct": 0.007835057870810678,
          "markup_range": 0.0014974920665734525,
          "min_markup": 0.004294807546401474,
          "n_close_orders": 8,
          "rentry_pprice_dist": 0.026250617338084755,
          "rentry_pprice_dist_wallet_exposure_weighting": 3.926149690487413,
          "wallet_exposure_limit": 1},
 "short": {"auto_unstuck_delay_minutes": 0,
           "auto_unstuck_ema_dist": 0,
           "auto_unstuck_qty_pct": 0,
           "auto_unstuck_wallet_exposure_threshold": 0.0,
           "backwards_tp": true,
           "ddown_factor": 1.2184278145332084,
           "ema_span_0": 1147.806786611839,
           "ema_span_1": 604.3229873292835,
           "enabled": true,
           "initial_eprice_ema_dist": -0.002885397739259701,
           "initial_qty_pct": 0.008567943701264591,
           "markup_range": 0.009818284973734609,
           "min_markup": 0.005396789570177937,
           "n_close_orders": 16,
           "rentry_pprice_dist": 0.029991143408882672,
           "rentry_pprice_dist_wallet_exposure_weighting": 4.277115810301703,
           "wallet_exposure_limit": 1}}