{"config_name": "recursive_grid_0days",
 "logging_level": 0,
 "long": {"auto_unstuck_delay_minutes": 120,
          "auto_unstuck_ema_dist": 0,
          "auto_unstuck_qty_pct": 0.01,
          "auto_unstuck_wallet_exposure_threshold": 0.05,
          "backwards_tp": true,
          "ddown_factor": 0.7526469730000345,
          "ema_span_0": 1414.4305370422774,
          "ema_span_1": 1264.3392455274534,
          "enabled": true,
          "initial_eprice_ema_dist": 0.002995531317611509,
          "initial_qty_pct": 0.011477399331464369,
          "markup_range": 0.005520152543961509,
          "min_markup": 0.004058196600437843,
          "n_close_orders": 7,
          "rentry_pprice_dist": 0.04787822822802025,
          "rentry_pprice_dist_wallet_exposure_weighting": 4.490505676745629,
          "wallet_exposure_limit": 1},
 "short": {"auto_unstuck_delay_minutes": 120,
           "auto_unstuck_ema_dist": 0,
           "auto_unstuck_qty_pct": 0.01,
           "auto_unstuck_wallet_exposure_threshold": 0.05,
           "backwards_tp": true,
           "ddown_factor": 2.21155553819479,
           "ema_span_0": 760.8861341175993,
           "ema_span_1": 1230.3412726627334,
           "enabled": true,
           "initial_eprice_ema_dist": 0.003,
           "initial_qty_pct": 0.01546217611586069,
           "markup_range": 0.003512257157953961,
           "min_markup": 0.0077470006321580555,
           "n_close_orders": 8,
           "rentry_pprice_dist": 0.049247338352128876,
           "rentry_pprice_dist_wallet_exposure_weighting": 10.146636774563685,
           "wallet_exposure_limit": 1}}