{"config_name": "recursive_grid_0days",
 "logging_level": 0,
 "long": {"auto_unstuck_delay_minutes": 0,
          "auto_unstuck_ema_dist": 0,
          "auto_unstuck_qty_pct": 0,
          "auto_unstuck_wallet_exposure_threshold": 0.0,
          "backwards_tp": true,
          "ddown_factor": 0.7649611174407369,
          "ema_span_0": 1129.7774722153606,
          "ema_span_1": 1064.0404572651694,
          "enabled": true,
          "initial_eprice_ema_dist": 0.002085785152088163,
          "initial_qty_pct": 0.012836892205500928,
          "markup_range": 0.0024747067053958426,
          "min_markup": 0.007622730581296063,
          "n_close_orders": 5,
          "rentry_pprice_dist": 0.036453625401409985,
          "rentry_pprice_dist_wallet_exposure_weighting": 1.1086465307812927,
          "wallet_exposure_limit": 1},
 "short": {"auto_unstuck_delay_minutes": 0,
           "auto_unstuck_ema_dist": 0,
           "auto_unstuck_qty_pct": 0,
           "auto_unstuck_wallet_exposure_threshold": 0.0,
           "backwards_tp": true,
           "ddown_factor": 0.21121918030792172,
           "ema_span_0": 721.8896248656592,
           "ema_span_1": 1360.6130392354266,
           "enabled": true,
           "initial_eprice_ema_dist": -0.007330703523834837,
           "initial_qty_pct": 0.01289300914932402,
           "markup_range": 0.0032900040213383356,
           "min_markup": 0.007917111424929492,
           "n_close_orders": 5,
           "rentry_pprice_dist": 0.03911008496356426,
           "rentry_pprice_dist_wallet_exposure_weighting": 2.5842375396326758,
           "wallet_exposure_limit": 1}}