{"config_name": "recursive_grid_0days",
 "logging_level": 0,
 "long": {"auto_unstuck_delay_minutes": 1278.996979400655,
          "auto_unstuck_ema_dist": -0.005095945747115762,
          "auto_unstuck_qty_pct": 0.010437833694009597,
          "auto_unstuck_wallet_exposure_threshold": 0.43353055026998355,
          "backwards_tp": true,
          "ddown_factor": 1.9836144046390243,
          "ema_span_0": 1076.0545519374782,
          "ema_span_1": 638.5290090706092,
          "enabled": true,
          "initial_eprice_ema_dist": 0.0014032922034565858,
          "initial_qty_pct": 0.016290328963882807,
          "markup_range": 0.002817224975068753,
          "min_markup": 0.0036817614702290904,
          "n_close_orders": 3,
          "rentry_pprice_dist": 0.02371655061670369,
          "rentry_pprice_dist_wallet_exposure_weighting": 2.823869714891594,
          "wallet_exposure_limit": 1},
 "short": {"auto_unstuck_delay_minutes": 759.7092354986778,
           "auto_unstuck_ema_dist": 0.0016741419562353332,
           "auto_unstuck_qty_pct": 0.056866036777620164,
           "auto_unstuck_wallet_exposure_threshold": 0.6685459317083094,
           "backwards_tp": true,
           "ddown_factor": 0.8342487851458049,
           "ema_span_0": 1033.5345838542275,
           "ema_span_1": 503.02104388707306,
           "enabled": true,
           "initial_eprice_ema_dist": -0.06776634583419447,
           "initial_qty_pct": 0.011870794577531872,
           "markup_range": 2.727638256273112e-06,
           "min_markup": 0.004941441902873034,
           "n_close_orders": 2,
           "rentry_pprice_dist": 0.02761745664847703,
           "rentry_pprice_dist_wallet_exposure_weighting": 0.011306626174140131,
           "wallet_exposure_limit": 1}}